mlend/__init__.py
mlend/downloader.py
mlend/processing.py
mlend-1.0.0.4.dist-info/LICENSE
mlend-1.0.0.4.dist-info/METADATA
mlend-1.0.0.4.dist-info/WHEEL
mlend-1.0.0.4.dist-info/top_level.txt
mlend-1.0.0.4.dist-info/RECORD
