Metadata-Version: 2.1
Name: mlend
Version: 1.0.0.4
Summary: MLEnd Datasets
Home-page: https://MLEndDatasets.github.io
Download-URL: https://github.com/Nikeshbajaj/MLEnd/tarball/1.0.0.4
Author: Jesús Requena Carrión and Nikesh Bajaj
Author-email: nikkeshbajaj@gmail.com
Maintainer: Nikesh Bajaj
Maintainer-email: nikkeshbajaj@gmail.com
License: MIT
Project-URL: Documentation, https://mlend.readthedocs.io/
Project-URL: Say Thanks!, https://github.com/Nikeshbajaj
Project-URL: Source, https://github.com/Nikeshbajaj/MLEnd
Project-URL: Tracker, https://github.com/Nikeshbajaj/MLEnd/issues
Keywords: MLEndDatasets Datasets MachineLearning PrinciplesOfMachineLearning Data AI
Platform: any
Classifier: Programming Language :: Python :: 3
Classifier: Programming Language :: Python :: 3.5
Classifier: Programming Language :: Python :: 3.6
Classifier: Programming Language :: Python :: 3.7
Classifier: Natural Language :: English
Classifier: License :: OSI Approved :: MIT License
Classifier: Operating System :: OS Independent
Classifier: Development Status :: 5 - Production/Stable
Classifier: Topic :: Scientific/Engineering :: Artificial Intelligence
Classifier: Topic :: Scientific/Engineering :: Information Analysis
Classifier: Topic :: Software Development :: Libraries :: Python Modules
Classifier: Topic :: Multimedia
Classifier: Topic :: Multimedia :: Sound/Audio :: Analysis
Classifier: Topic :: Multimedia :: Sound/Audio :: Speech
Classifier: Topic :: Scientific/Engineering :: Image Processing
Classifier: Topic :: Scientific/Engineering :: Visualization
Classifier: Intended Audience :: Developers
Classifier: Intended Audience :: Science/Research
Classifier: Intended Audience :: Education
Classifier: Development Status :: 5 - Production/Stable
Requires-Python: >=3.5
License-File: LICENSE
Requires-Dist: numpy <2.0
Requires-Dist: pandas
Requires-Dist: scipy
Requires-Dist: matplotlib
Requires-Dist: joblib
Requires-Dist: spkit
